astropy_helpers/__init__.py
astropy_helpers/conftest.py
astropy_helpers/distutils_helpers.py
astropy_helpers/git_helpers.py
astropy_helpers/openmp_helpers.py
astropy_helpers/setup_helpers.py
astropy_helpers/utils.py
astropy_helpers/version_helpers.py
astropy_helpers/commands/__init__.py
astropy_helpers/commands/_dummy.py
astropy_helpers/commands/build_ext.py
astropy_helpers/commands/build_sphinx.py
astropy_helpers/commands/test.py
astropy_helpers/sphinx/__init__.py
astropy_helpers/sphinx/conf.py
astropy_helpers/tests/__init__.py
astropy_helpers/tests/test_ah_bootstrap.py
astropy_helpers/tests/test_git_helpers.py
astropy_helpers/tests/test_openmp_helpers.py
astropy_helpers/tests/test_setup_helpers.py
astropy_helpers/tests/test_utils.py
atomicdataMB/__init__.py
atomicdataMB/atomicmass.py
atomicdataMB/configure_database.py
atomicdataMB/database_connect.py
atomicdataMB/g_values.py
atomicdataMB/initialize_atomicdata.py
atomicdataMB/make_photo_table.py
atomicdataMB/photolossrates.py
atomicdataMB/version.py
atomicdataMB/data/Loss/Photo/Berezhnoy2008.dat
atomicdataMB/data/Loss/Photo/Berezhnoy2013.dat
atomicdataMB/data/Loss/Photo/Huebner2011.dat
atomicdataMB/data/Loss/Photo/photo_rates.pickle
atomicdataMB/data/g-values/.DS_Store
atomicdataMB/data/g-values/C.Killen2009.dat
atomicdataMB/data/g-values/Ca+.Killen2009.dat
atomicdataMB/data/g-values/Ca.4227.KillenXXXX.dat
atomicdataMB/data/g-values/Ca.Killen2009.dat
atomicdataMB/data/g-values/Ca.Killen2009.dat.old
atomicdataMB/data/g-values/Ca_gval_50_354.txt
atomicdataMB/data/g-values/H.Killen2009.dat
atomicdataMB/data/g-values/He.Killen2009.dat
atomicdataMB/data/g-values/K.Killen2009.dat
atomicdataMB/data/g-values/Mg+.Killen2009.dat
atomicdataMB/data/g-values/Mg.Killen2009.dat.old
atomicdataMB/data/g-values/Mg.KillenXXXX.dat
atomicdataMB/data/g-values/Mn.KillenXXXX.dat
atomicdataMB/data/g-values/Na.3303.Killen2009.dat
atomicdataMB/data/g-values/Na.D1.KillenXXXX.dat
atomicdataMB/data/g-values/Na.D2.KillenXXXX.dat
atomicdataMB-1.1.9.dist-info/LICENSE.rst
atomicdataMB-1.1.9.dist-info/METADATA
atomicdataMB-1.1.9.dist-info/WHEEL
atomicdataMB-1.1.9.dist-info/top_level.txt
atomicdataMB-1.1.9.dist-info/RECORD
