Metadata-Version: 2.1
Name: atomicdataMB
Version: 1.1.9
Summary: Atomic data procedures for nexoclom and general use
Home-page: https://github.com/mburger-stsci/atomicdataMB
Author: Matthew Burger
Author-email: mburger@stsci.edu
License: BSD 3-Clause
Platform: UNKNOWN
Requires-Python: >=3.6
Requires-Dist: mathMB
Requires-Dist: psycopg2
Requires-Dist: pandas
Requires-Dist: periodictable
Requires-Dist: astropy
